emojiization/__init__.py
emojiization/functions/__init__.py
emojiization/functions/metrics.py
emojiization/functions/transform.py
emojiization-0.0.2.dist-info/METADATA
emojiization-0.0.2.dist-info/WHEEL
emojiization-0.0.2.dist-info/top_level.txt
emojiization-0.0.2.dist-info/RECORD
