Metadata-Version: 2.1
Name: emojiization
Version: 0.0.2
Summary: O pacote emojiization foi desenvolvido pelo time do dadosaocubo.com para tratamento de textos com Emojis
Home-page: https://github.com/dadosaocubo/emojiization-package
Author: Dados ao Cubo
Author-email: tiago@dadosaocubo.com
License: UNKNOWN
Platform: UNKNOWN
Requires-Python: >=3.8
Requires-Dist: emoji (==1.7.0)
